{
  "based_on_render_metadata": "tmp/p5_contract_check/render/metadata.json",
  "command": [
    "make"
  ],
  "discovered_tests": [],
  "duration_seconds": 0.005261,
  "end_time": "2026-03-27T14:58:15.635863+00:00",
  "executed_tests": [],
  "execution_notes": [
    "Simulation stage consumes render metadata and package artifacts without modifying rendered test semantics.",
    "Selected backend 'make' for mode 'make'.",
    "No explicit per-test results were found in logs; relying on return code and JUnit when available."
  ],
  "failed_tests": [],
  "junit_path": null,
  "log_paths": {
    "build_log": "tmp/p5_contract_run/run/logs/build.log",
    "stderr": "tmp/p5_contract_run/run/logs/stderr.txt",
    "stdout": "tmp/p5_contract_run/run/logs/stdout.txt",
    "test_log": "tmp/p5_contract_run/run/logs/test.log"
  },
  "module_name": "simple_comb",
  "passed_tests": [],
  "return_code": 2,
  "runner_warnings": [],
  "selected_mode": "make",
  "selected_simulator": "icarus",
  "skipped_tests": [],
  "start_time": "2026-03-27T14:58:15.630602+00:00",
  "status": "environment_error",
  "waveform_paths": []
}